magix/__init__.py
magix-0.1.2.dist-info/METADATA
magix-0.1.2.dist-info/WHEEL
magix-0.1.2.dist-info/RECORD
