Metadata-Version: 2.3
Name: magix
Version: 0.1.2
Summary: Graph database object mapper.
License: MIT
Author: Jakob Kristensen
Author-email: jakob@jakobk.dk
Requires-Python: >=3.13,<4.0
Classifier: License :: OSI Approved :: MIT License
Classifier: Programming Language :: Python :: 3
Classifier: Programming Language :: Python :: 3.13
